pkg/__init__.py
closet_engine_cv-0.2.1.dist-info/LICENSE
closet_engine_cv-0.2.1.dist-info/METADATA
closet_engine_cv-0.2.1.dist-info/WHEEL
closet_engine_cv-0.2.1.dist-info/entry_points.txt
closet_engine_cv-0.2.1.dist-info/top_level.txt
closet_engine_cv-0.2.1.dist-info/RECORD
