Metadata-Version: 2.1
Name: closet-engine-cv
Version: 0.2.1
Summary: A small example package
Home-page: https://github.com/pypa/sampleproject
Author: Ingun Jon
Author-email: ingun37@gmail.com
Classifier: Programming Language :: Python :: 3
Classifier: License :: OSI Approved :: MIT License
Classifier: Operating System :: OS Independent
Requires-Python: >=3.7
License-File: LICENSE
Requires-Dist: opencv-python
